csbaoyan/__init__.py
csbaoyan-0.0.1.dist-info/METADATA
csbaoyan-0.0.1.dist-info/WHEEL
csbaoyan-0.0.1.dist-info/entry_points.txt
csbaoyan-0.0.1.dist-info/top_level.txt
csbaoyan-0.0.1.dist-info/RECORD
