Metadata-Version: 2.1
Name: csbaoyan
Version: 0.0.1
Summary: 计算机保研交流群
Home-page: https://csbaoyan.nonexist
Author: csbaoyan
Author-email: csbaoyan@nonexist.com
License: UNKNOWN
Platform: UNKNOWN
Requires-Dist: requests
